chaosplatform/__init__.py
chaosplatform/__main__.py
chaosplatform/api.py
chaosplatform/app.py
chaosplatform/auth.py
chaosplatform/cache.py
chaosplatform/cli.py
chaosplatform/log.py
chaosplatform/logging.json
chaosplatform/server.py
chaosplatform/settings.py
chaosplatform/storage.py
chaosplatform/service/__init__.py
chaosplatform/views/__init__.py
chaosplatform-0.2.0.dist-info/LICENSE
chaosplatform-0.2.0.dist-info/METADATA
chaosplatform-0.2.0.dist-info/WHEEL
chaosplatform-0.2.0.dist-info/entry_points.txt
chaosplatform-0.2.0.dist-info/top_level.txt
chaosplatform-0.2.0.dist-info/RECORD
