Metadata-Version: 2.1
Name: chaosplatform
Version: 0.2.0
Summary: The control plane of the Chaos Platform
Home-page: https://github.com/chaostoolkit/chaoshub
Author: ChaosIQ
Author-email: contact@chaosiq.io
License: Apache Software License 2.0
Project-URL: CI: Travis, https://travis-ci.org/chaostoolkit/chaosplatform
Project-URL: Docs: RTD, https://docs.chaosplatform.org
Project-URL: GitHub: issues, https://chaostoolkit/chaostoolkit/chaosplatform/issues
Project-URL: GitHub: repo, https://chaostoolkit/chaostoolkit/chaosplatform
Platform: UNKNOWN
Classifier: Development Status :: 4 - Beta
Classifier: Intended Audience :: Developers
Classifier: License :: OSI Approved :: Apache Software License
Classifier: Operating System :: Unix
Classifier: Operating System :: POSIX
Classifier: Programming Language :: Python
Classifier: Programming Language :: Python :: 3
Classifier: Programming Language :: Python :: 3.6
Classifier: Programming Language :: Python :: 3.7
Classifier: Programming Language :: Python :: 3 :: Only
Classifier: Programming Language :: Python :: Implementation :: CPython
Requires-Python: >=3.6.*
Requires-Dist: Click (>=7.0)
Requires-Dist: flask (>=1.0.2)
Requires-Dist: flask-jwt-extended (>=3.14.0)
Requires-Dist: cryptography (>=2.3.1)
Requires-Dist: itsdangerous (>=0.24)
Requires-Dist: flask-caching (>=1.4.0)
Requires-Dist: cherrypy (>=18.0.1)
Requires-Dist: wsgi-request-logger (>=0.4.6)
Requires-Dist: Flask-SQLAlchemy (>=2.3.2)
Requires-Dist: Flask-Dance (>=1.2.0)
Requires-Dist: Flask-Dance[sqla] (>=1.2.0)
Requires-Dist: Flask-Login (>=0.4.1)
Requires-Dist: simplejson (>=3.15.0)
Requires-Dist: sqlalchemy (>=1.2.8)
Requires-Dist: sqlalchemy-utils (>=0.33.3)
Requires-Dist: sqlalchemy-json (>=0.2.1)
Requires-Dist: grpcio (>=1.17.1)
Requires-Dist: apispec (>=0.39.0)
Requires-Dist: marshmallow-sqlalchemy (>=0.15.0)
Requires-Dist: chaosplatform-grpc (>=0.1.1)
Requires-Dist: chaosplatform-relational-storage (>=0.2.2)
Requires-Dist: chaosplatform-auth (>=0.3.0)
Requires-Dist: chaosplatform-account (>=0.2.0)
Requires-Dist: chaosplatform-experiment (>=0.2.0)
Requires-Dist: chaosplatform-scheduling (>=0.2.0)
Requires-Dist: chaosplatform-scheduler (>=0.2.0)
Requires-Dist: toml (>=0.10.0)
